VIVA/__init__.py
VIVA/gui.py
VIVA/maaain.py
VIVA/main.py
VIVAA_RAHA1-0.1.0.dist-info/LICENCE
VIVAA_RAHA1-0.1.0.dist-info/METADATA
VIVAA_RAHA1-0.1.0.dist-info/WHEEL
VIVAA_RAHA1-0.1.0.dist-info/entry_points.txt
VIVAA_RAHA1-0.1.0.dist-info/top_level.txt
VIVAA_RAHA1-0.1.0.dist-info/RECORD
