Metadata-Version: 2.1
Name: VIVAA-RAHA1
Version: 0.1.0
Summary: A description of your package
Author: VISHNU_VARDHAN
Author-email: vardhan101101@gmail.com
Classifier: Programming Language :: Python :: 3
Classifier: License :: OSI Approved :: MIT License
Classifier: Operating System :: OS Independent
Requires-Python: >=3.6
License-File: LICENCE
Requires-Dist: FreeSimpleGUI
Requires-Dist: opencv-python
